{
    "id": 48175126,
    "name": "Moment",
    "author": "Icedcave",
    "creators": ["Icedcave"],
    "verifier": "Chloe",
    "verification": "https://www.youtube.com/watch?v=HHpmYqJloXo",
    "percentToQualify": 100,
    "password": "Copyable",
    "records": [
         {
            "user": "nairda",
            "link": "https://youtu.be/jrgkmPP9tbM?si=iBaij8LAaNUhgUjO",
            "percent": 100,
            "hz": 240
        },
        {
            "user": "Meridiem",
            "link": "https://youtu.be/he6KRQuG704?si=bDRVmHeNKeh6-5y8",
            "percent": 100,
            "hz": 240
        }
    ]
}
